{
  "accuracy_val": 0.8893846153846154,
  "training_time": 220.25216555595398,
  "log": [
    {
      "epoch": 0,
      "loss": 1.9608829021453857,
      "accuracy": 0.5858461538461538,
      "learning_rate": 0.001
    },
    {
      "epoch": 1,
      "loss": 1.8077647686004639,
      "accuracy": 0.7007692307692308,
      "learning_rate": 0.001
    },
    {
      "epoch": 2,
      "loss": 1.7802270650863647,
      "accuracy": 0.742,
      "learning_rate": 0.001
    },
    {
      "epoch": 3,
      "loss": 1.643897533416748,
      "accuracy": 0.7744615384615384,
      "learning_rate": 0.001
    },
    {
      "epoch": 4,
      "loss": 1.5753393173217773,
      "accuracy": 0.794923076923077,
      "learning_rate": 0.001
    },
    {
      "epoch": 5,
      "loss": 1.5423965454101562,
      "accuracy": 0.8121538461538461,
      "learning_rate": 0.001
    },
    {
      "epoch": 6,
      "loss": 1.4915826320648193,
      "accuracy": 0.8215384615384616,
      "learning_rate": 0.001
    },
    {
      "epoch": 7,
      "loss": 1.5065847635269165,
      "accuracy": 0.8341538461538461,
      "learning_rate": 0.001
    },
    {
      "epoch": 8,
      "loss": 1.4544841051101685,
      "accuracy": 0.8353846153846154,
      "learning_rate": 0.001
    },
    {
      "epoch": 9,
      "loss": 1.2615313529968262,
      "accuracy": 0.8492307692307692,
      "learning_rate": 0.001
    },
    {
      "epoch": 10,
      "loss": 1.3816893100738525,
      "accuracy": 0.8541538461538462,
      "learning_rate": 0.001
    },
    {
      "epoch": 11,
      "loss": 1.3527522087097168,
      "accuracy": 0.8575384615384616,
      "learning_rate": 0.001
    },
    {
      "epoch": 12,
      "loss": 1.2078932523727417,
      "accuracy": 0.8626153846153846,
      "learning_rate": 0.001
    },
    {
      "epoch": 13,
      "loss": 1.223300576210022,
      "accuracy": 0.86,
      "learning_rate": 0.001
    },
    {
      "epoch": 14,
      "loss": 1.3448299169540405,
      "accuracy": 0.8724615384615385,
      "learning_rate": 0.001
    },
    {
      "epoch": 15,
      "loss": 1.237251877784729,
      "accuracy": 0.8730769230769231,
      "learning_rate": 0.001
    },
    {
      "epoch": 16,
      "loss": 1.2299084663391113,
      "accuracy": 0.8726153846153846,
      "learning_rate": 0.001
    },
    {
      "epoch": 17,
      "loss": 1.281754732131958,
      "accuracy": 0.8755384615384615,
      "learning_rate": 0.001
    },
    {
      "epoch": 18,
      "loss": 1.365372657775879,
      "accuracy": 0.8810769230769231,
      "learning_rate": 0.001
    },
    {
      "epoch": 19,
      "loss": 1.3116756677627563,
      "accuracy": 0.8724615384615385,
      "learning_rate": 0.001
    },
    {
      "epoch": 20,
      "loss": 1.3067538738250732,
      "accuracy": 0.8807692307692307,
      "learning_rate": 0.001
    },
    {
      "epoch": 21,
      "loss": 1.2843225002288818,
      "accuracy": 0.8890769230769231,
      "learning_rate": 0.001
    },
    {
      "epoch": 22,
      "loss": 1.2321678400039673,
      "accuracy": 0.884,
      "learning_rate": 0.001
    },
    {
      "epoch": 23,
      "loss": 1.1872851848602295,
      "accuracy": 0.8776923076923077,
      "learning_rate": 0.001
    },
    {
      "epoch": 24,
      "loss": 1.2187061309814453,
      "accuracy": 0.8849230769230769,
      "learning_rate": 0.001
    },
    {
      "epoch": 25,
      "loss": 1.2398629188537598,
      "accuracy": 0.8895384615384615,
      "learning_rate": 0.001
    },
    {
      "epoch": 26,
      "loss": 1.2392135858535767,
      "accuracy": 0.8876923076923077,
      "learning_rate": 0.001
    },
    {
      "epoch": 27,
      "loss": 1.194611668586731,
      "accuracy": 0.8892307692307693,
      "learning_rate": 0.001
    },
    {
      "epoch": 28,
      "loss": 1.245063304901123,
      "accuracy": 0.8921538461538462,
      "learning_rate": 0.001
    },
    {
      "epoch": 29,
      "loss": 1.215376615524292,
      "accuracy": 0.8943076923076924,
      "learning_rate": 0.001
    }
  ],
  "name": "",
  "description": "",
  "folder": "LSTM_50",
  "model": {
    "architecture": "LSTM",
    "num_layers": 1,
    "hidden_units": 50,
    "filename": "LSTM50KeywordSpotter.pt"
  },
  "dataset": {
    "name": "speechcommandsv01",
    "featurizer": "featurizer_mel_16000_512_512_80_40_log",
    "categories": "categories.txt",
    "path": "d:\\temp\\TrainKeywordSpotter_v01\\featurizer_mel_16000_512_512_80_40_log",
    "auto_scale": true,
    "sample_rate": 16000,
    "input_size": 512,
    "num_filters": 80,
    "window_size": 40,
    "shift": 40
  },
  "training": {
    "max_epochs": 30,
    "learning_rate": 0.001,
    "lr_scheduler": null,
    "lr_peaks": 0,
    "lr_min": 0.001,
    "batch_size": 100,
    "optimizer": "RMSprop",
    "optimizer_options": {
      "weight_decay": 1e-06,
      "momentum": 0,
      "centered": false,
      "alpha": 0.99,
      "eps": 1e-08,
      "rho": 0,
      "lr_decay": 0,
      "betas": [
        0.9,
        0.999
      ],
      "lambd": 0.0001,
      "t0": 1000000.0,
      "etas": [
        0.5,
        1.2
      ],
      "dampening": 0,
      "step_sizes": [
        1e-06,
        50
      ]
    },
    "use_gpu": true
  },
  "job_id": null,
  "status": null,
  "downloaded": false,
  "last_modified": 1556608814.9614384,
  "retries": 0,
  "filename": "LSTM_50\\options.json",
  "sweep": "hidden_units"
}